{
  "Author": "Det",
  "Name": "(old) Auto Hook",
  "Punchline": "New Repo: https://love.puni.sh/ment.json",
  "Description": "It hooks the fish for you, can you believe it?",
  "InternalName": "AutoHook",
  "RepoUrl": "https://puni.sh/plugin/AutoHook",
  "ApplicableVersion": "any",
  "Tags": [ "Gathering", "Fishing" ],
  "DalamudApiLevel": 9,
  "AcceptsFeedback": false,
  "IconUrl": "https://raw.githubusercontent.com/InitialDet/AutoHook/main/AutoHook/images/icon.png",
  "Changelog": "Click the new Changelog button to see whats new"
}